zip_shotgun/__init__.py
zip_shotgun/zip_shotgun_main.py
zip_shotgun/shells/__init__.py
zip_shotgun/shells/wwwolf_php_webshell.py
zip_shotgun/zip_shotugn_utils/__init__.py
zip_shotgun/zip_shotugn_utils/utils.py
zip_shotgun-1.0.2.dist-info/LICENSE
zip_shotgun-1.0.2.dist-info/METADATA
zip_shotgun-1.0.2.dist-info/WHEEL
zip_shotgun-1.0.2.dist-info/entry_points.txt
zip_shotgun-1.0.2.dist-info/top_level.txt
zip_shotgun-1.0.2.dist-info/RECORD
