Metadata-Version: 2.1
Name: zip-shotgun
Version: 1.0.2
Summary: Utility script to test zip file upload functionality (and possible extraction of zip files) for vulnerabilities
Home-page: https://github.com/jpiechowka/zip-shotgun
Author: Janusz Piechówka (https://github.com/jpiechowka)
License: GNU General Public License v3.0
Keywords: security pentest hacking zip
Platform: UNKNOWN
Classifier: Development Status :: 5 - Production/Stable
Classifier: Intended Audience :: Developers
Classifier: Intended Audience :: End Users/Desktop
Classifier: Intended Audience :: Information Technology
Classifier: Intended Audience :: System Administrators
Classifier: Programming Language :: Python :: 3
Classifier: Programming Language :: Python :: Implementation :: CPython
Classifier: Environment :: Console
Classifier: Natural Language :: English
Classifier: Operating System :: OS Independent
Classifier: Topic :: Security
Classifier: Topic :: Utilities
Classifier: License :: OSI Approved :: GNU General Public License v3 (GPLv3)
Requires-Python: >=3.6
Requires-Dist: click (~=7.0)
Requires-Dist: typeguard (~=2.2)
